{
  "schema_version": 3,
  "id": "yue_he",
  "name_zh": "乐和",
  "name_en": "Yue He",
  "aliases": [
    "铁叫子",
    "地乐星"
  ],
  "epithet": "铁叫子·地乐星·登州孙立小舅",
  "category": "liangshan",
  "era_layer": 0,
  "bio": "乐和，古典名著《水浒传》中的人物，绰号“铁叫子”，一百单八将之一，排第七十七位，地乐星。茅州（今山东昌邑）人氏，善奏乐演唱，亦习武艺。因姐姐嫁与孙立为妻，凭借这层关系做了登州（今山东蓬莱）监狱的狱卒。解珍、解宝兄弟被毛太公陷害入狱后，乐和同情二人，联系孙新、顾大嫂等人，联合邹渊、邹润，于夜间劫狱救出解家兄弟，并一同杀死毛太公全家。随后众人投奔梁山，途经祝家庄时，孙立利用与教头栾廷玉的同门关系，携乐和等人卧底庄内，配合梁山军第三次攻破祝家庄，立下大功。梁山聚义后，乐和担任走报机密步军头领，负责传递情报。高俅征讨梁山被俘，宋江释放高俅并派乐和与萧让陪同回京面圣，以表招安诚意。高俅食言，将乐和与萧让扣留府中，幸得戴宗、燕青营救脱险。梁山受招安后，乐和参与征辽、讨田虎、王庆等战役，多有贡献。征方腊前，王都尉（驸马）听闻乐和音乐才华，奏请皇帝将其留在府中任用，乐和因而未参与征方腊之战，得以善终。",
  "events": [
    {
      "title": "劫狱救解珍解宝",
      "desc": "解珍、解宝兄弟被毛太公陷害入狱，毛太公贿赂狱卒欲暗杀二人。乐和同情二人，秘密通知顾大嫂、孙新，并联络邹渊、邹润，于夜间劫狱，乐和趁机释放解氏兄弟。事后众人杀死毛太公全家，决意投奔梁山。",
      "source": {
        "work": "水浒传",
        "locus": null,
        "translator": null
      },
      "canon": null
    },
    {
      "title": "卧底祝家庄",
      "desc": "孙立以同门师兄弟身份投靠祝家庄教头栾廷玉，乐和与顾大嫂、孙新等扮作随从一同进入。孙立假意擒获梁山石秀取得信任，最终里应外合，助梁山军攻破祝家庄，乐和在此次行动中协助传递消息。",
      "source": {
        "work": "水浒传",
        "locus": null,
        "translator": null
      },
      "canon": null
    },
    {
      "title": "送高俅回京被扣",
      "desc": "高俅被梁山俘虏后释放，宋江派乐和与萧让护送高俅回京，以求招安。高俅背信弃义，将二人软禁在府中。戴宗与燕青暗中监视，趁夜救出乐和与萧让。",
      "source": {
        "work": "水浒传",
        "locus": null,
        "translator": null
      },
      "canon": null
    },
    {
      "title": "被王都尉征召",
      "desc": "征讨方腊前夕，王都尉（驸马）听闻乐和音乐才华，奏请宋徽宗将乐和留在府中任用。乐和因此未参与征方腊之战，在都尉府中度过余生，得以善终。",
      "source": {
        "work": "水浒传",
        "locus": null,
        "translator": null
      },
      "canon": null
    }
  ],
  "quotes": [],
  "weapons": [],
  "skills": [
    "演奏乐器",
    "歌唱",
    "格斗"
  ],
  "domains": [
    "情报",
    "音乐"
  ],
  "mounts": [],
  "portrait": "/p/shuihu/portraits/yue_he.webp",
  "thumb": "/p/shuihu/thumbs/yue_he.webp"
}