{
  "schema_version": 3,
  "id": "cheng_yu",
  "name_zh": "程昱",
  "name_en": "Cheng Yu",
  "aliases": [
    "程立",
    "仲德"
  ],
  "epithet": "魏国谋臣·刚戾多谋",
  "category": "wei",
  "era_layer": 2,
  "bio": "程昱（141年－220年），本名程立，字仲德，兖州东郡东阿（今山东东阿）人。他身高约一米九一，长须，容貌威严。早年在家乡以勇略闻名。黄巾起义时，他设计智破王度，保全东阿。后刘岱征辟，程昱辞而不就。曹操入主兖州后，程昱欣然应召，被任命为寿张令。吕布进攻兖州时，程昱与荀彧留守，力保三城，为曹操稳住后方。他曾劝曹操杀刘备，曹操未从；后又预言刘备借兵必叛，果如其言。官渡之战前，程昱以七百兵守城，拒袁绍十万大军，曹操赞其智勇。战后，他招募兵众，与李典北渡河破高蕃，打通水路。赤壁之战前，程昱准确判断孙权必与刘备联合，但曹操未予重视。魏国建立后，程昱任卫尉，因与中尉邢贞争威仪被罢免。曹丕称帝后，复为卫尉，进封安乡侯。朝廷欲以程昱为三公，然其于220年十二月去世，享年八十。程昱多谋善断，性格刚戾，与人不合，被时人评为“勇冠贲育”。",
  "events": [
    {
      "title": "设计破王度，保全东阿",
      "desc": "黄巾起义时，县尉王度焚烧仓库，欲夺城。程昱设计使百姓误以为黄巾军来袭，驱民回城，并寻回县令，组织防御，击退王度，保住了东阿县。",
      "source": {
        "work": "三国志·程昱传",
        "locus": null,
        "translator": null
      },
      "canon": null
    },
    {
      "title": "拒绝刘岱征辟",
      "desc": "兖州刺史刘岱多次征召程昱，程昱均拒绝。后刘岱因与袁绍、公孙瓒关系紧张，程昱为其分析利害，劝其断绝与公孙瓒的往来，刘岱听从，但程昱仍未应召。",
      "source": {
        "work": "三国志·程昱传",
        "locus": null,
        "translator": null
      },
      "canon": null
    },
    {
      "title": "归附曹操，任寿张令",
      "desc": "曹操入主兖州后，程昱应召成为其部下，被任命为寿张令。尽管职位低于刘岱曾许诺的官职，程昱仍决心追随曹操。",
      "source": {
        "work": "三国志·程昱传",
        "locus": null,
        "translator": null
      },
      "canon": null
    },
    {
      "title": "与荀彧共守三城，抵御吕布",
      "desc": "吕布攻占兖州时，唯鄄城、东阿、范县未降。程昱与荀彧合作，亲自赴东阿及范县说服守将，斩杀吕布部将氾嶷，并派兵控制仓亭津，阻止陈宫，直到曹操回援。",
      "source": {
        "work": "三国志·程昱传",
        "locus": null,
        "translator": null
      },
      "canon": null
    },
    {
      "title": "劝曹操杀刘备",
      "desc": "刘备投奔曹操后，程昱劝曹操早日除掉刘备，认为刘备有雄才且得众心，必不为下。曹操未从，后刘备果然借机叛离。",
      "source": {
        "work": "三国志·程昱传",
        "locus": null,
        "translator": null
      },
      "canon": null
    },
    {
      "title": "预言刘备借兵必叛",
      "desc": "刘备请求领兵拦截袁术，程昱闻讯急劝曹操不可借兵，断言刘备必叛。曹操后悔已晚，刘备果然杀死徐州刺史车胄，重新占据徐州。",
      "source": {
        "work": "三国志·程昱传",
        "locus": null,
        "translator": null
      },
      "canon": null
    },
    {
      "title": "以七百兵拒袁绍十万军",
      "desc": "官渡之战前夕，程昱率七百兵驻守鄄城。曹操欲增兵两千，程昱拒绝，认为兵少反使袁绍不敢轻易进攻，增兵反而易招致攻击。曹操从之，后袁绍果然未攻鄄城。",
      "source": {
        "work": "三国志·程昱传",
        "locus": null,
        "translator": null
      },
      "canon": null
    },
    {
      "title": "招募兵众，会师黎阳，破高蕃",
      "desc": "官渡战后，程昱招募数千山贼和百姓，与李典率军与曹操会师黎阳。在运粮途中，遭魏郡太守高蕃阻截，程昱与李典违令北渡河，击败高蕃，打通水道。",
      "source": {
        "work": "三国志·程昱传",
        "locus": null,
        "translator": null
      },
      "canon": null
    },
    {
      "title": "预测孙刘联盟",
      "desc": "赤壁之战前，曹操大兵压境，多数人认为孙权会杀刘备投降。程昱独排众议，认为孙权必会联合刘备抗击曹操，但曹操未予重视，后果然应验。",
      "source": {
        "work": "三国志·程昱传",
        "locus": null,
        "translator": null
      },
      "canon": null
    },
    {
      "title": "任卫尉，因争威仪被罢免",
      "desc": "魏国建立后，程昱任卫尉。因与中尉邢贞在朝会中争威仪礼节，被弹劾免官。",
      "source": {
        "work": "三国志·程昱传",
        "locus": null,
        "translator": null
      },
      "canon": null
    },
    {
      "title": "曹丕称帝后复官，进封安乡侯",
      "desc": "延康元年（220年），曹丕代汉称帝，程昱复任卫尉，进封安乡侯。朝廷欲以其为三公，但程昱随即去世，享年八十。",
      "source": {
        "work": "三国志·程昱传",
        "locus": null,
        "translator": null
      },
      "canon": null
    }
  ],
  "quotes": [],
  "weapons": [],
  "skills": [
    "运筹帷幄",
    "守城防御",
    "识人料事",
    "招募兵众",
    "分析战局"
  ],
  "domains": [
    "军事谋略",
    "州郡治理",
    "识人用人"
  ],
  "mounts": [],
  "portrait": "/p/sanguo/portraits/cheng_yu.webp",
  "thumb": "/p/sanguo/thumbs/cheng_yu.webp"
}